{
	"configurations" : 
	[
		{
			"directories" : 
			[
				{
					"build" : ".",
					"jsonFile" : "directory-.-Debug-f5ebdc15457944623624.json",
					"minimumCMakeVersion" : 
					{
						"string" : "3.0.0"
					},
					"projectIndex" : 0,
					"source" : ".",
					"targetIndexes" : 
					[
						0,
						1
					]
				}
			],
			"name" : "Debug",
			"projects" : 
			[
				{
					"directoryIndexes" : 
					[
						0
					],
					"name" : "leptjson_test",
					"targetIndexes" : 
					[
						0,
						1
					]
				}
			],
			"targets" : 
			[
				{
					"directoryIndex" : 0,
					"id" : "leptjson::@6890427a1f51a3e7e1df",
					"jsonFile" : "target-leptjson-Debug-49c08774ced290dffcf1.json",
					"name" : "leptjson",
					"projectIndex" : 0
				},
				{
					"directoryIndex" : 0,
					"id" : "leptjson_test::@6890427a1f51a3e7e1df",
					"jsonFile" : "target-leptjson_test-Debug-56305c4c11d505b6d29e.json",
					"name" : "leptjson_test",
					"projectIndex" : 0
				}
			]
		}
	],
	"kind" : "codemodel",
	"paths" : 
	{
		"build" : "/mnt/c/Users/AeonJh/AeonJh_PC/Documents/CLionProjects/leptjson_study/cmake-build-debug",
		"source" : "/mnt/c/Users/AeonJh/AeonJh_PC/Documents/CLionProjects/leptjson_study"
	},
	"version" : 
	{
		"major" : 2,
		"minor" : 3
	}
}
